{"Q8kyWdiPLYJ/4F1Ss+9IyA==":"03.jpg","3EoVKFBgSEuXQIQKIstd7A==":"3d%20city%2028.05-122x83.jpg","uWOtngNPRmMIjiJinZyzfg==":"52b11b0b3b75202f398725b6260f9430.gif","KPV8UwQ2zadd0a7jzqCx0w==":"mapping1-1280x861.jpg","DdTkXYbzPahdpmenWFzDvw==":"3dcityio_logo_white-178x162.png","qdjVv8gzlkciK5lJRG3/HA==":"mapping1-861x1280.jpg","N8oF/O4eZNhwOKO2xp5cBQ==":"sensor-data.gif","1U4j++ukJc+a27BQ5mPEhA==":"carlos-profile-160x131.jpg","pl5e72lCm2sMAk3dImAQ0w==":"yanita-160x160.jpg","J0cDgsbUPVOktXtVVHAfPQ==":"carlos-406x334.jpg","Cc6C2lvzhbSIQGb4cPeWwg==":"yana-510x510.jpg","31p19p7n7xo+WAdsSmry4w==":"37227492_10156357059273796_2961873163161436160_n-510x383.jpg","zWIs/vY6W5cQ2nmk/U8Tlg==":"37227492_10156357059273796_2961873163161436160_n-510x508.jpg","+fQx4DK9sNJBBtbuWukH/g==":"37227492_10156357059273796_2961873163161436160_n-1-510x508.jpg","w1eVADrMDP4DZh4MQYYZdw==":"camillo-510x510.png","RUep7ucBlK2ZmQc04Yh1BA==":"37227492_10156357059273796_2961873163161436160_n-2-510x508.jpg","AAwjDEz/7Ty38cqgS2Ii8A==":"yana-1-510x510.jpg","mo5eMIXirKTeIxTN8OP1+Q==":"carlos-1-406x334.jpg","PE9Dg+AYoKGFTOxnXZkknQ==":"1_pfkv8ub4vgwn9ufrt6iaza.gif","w5Z8fv3PFL98VbBmdsu1NA==":"1.gif","4+DzqXFpj/z2AIwVP9lcYQ==":"background5.jpg","Ly+mdm63lVz6CqSX2vcU6g==":"background3.jpg","pepS3qq82EEliwIGr/Hhjg==":"2.gif","wjzjN80cXAy97h+JfGYeDQ==":"1-1.gif","Mnd02cDWogHmmESdfrB99w==":"2-1.gif","QDxWJ54FxzeKbarh+dKlXw==":"guy_bw-510x508.jpg","OjyPcCPuovHBf1/2nYWK7A==":"camillo_bw-510x510.png","4pTTTPuOT6XyUHOP+yPz9g==":"yana_bw-510x510.jpg","z9G9Zow51fAU7RDnq/ASOQ==":"carlos-2-406x334.jpg","okHyZP5j+SpaIJv2K6Lksw==":"carlos-3-406x334.jpg","MDsADo7r2MrMYuoi419s2w==":"carlos-4-406x334.jpg","QYwJhvM3VKVc/GMgnmdb/A==":"guy_bw-1-510x508.jpg","3V9Onf3FicrBBB28OBuY6A==":"giphy-1.gif","V3B0d0OqJ0aJbcVXYB2B8A==":"52b11b0b3b75202f398725b6260f9430-min.gif","4viVw3k7lvKRqounN5pgDg==":"52b11b0b3b75202f398725b6260f9430-min-min.gif","XaZMwT1TWT980qzXRGSYYA==":"sensor-data-min.gif","UfWlLdj/HMO84ZIEobHDtg==":"1-min.gif","7Lh9gHENPCX5FqNDb6Ccfw==":"dr4.gif","VOR+yO7ZuhEqX7z6GBFRyA==":"tumblr_ozz9j92yhi1qav3uso1-500.gif","RuMWOd8Chdo7HGSBc30xuA==":"1_q1uvc-mu-tc-wwfp2yxjow-299x168.jpg","rgYPtK1rDxudITkBb8pNxw==":"images-300x168.jpg","UUai4eQimpPKi5evDOChsQ==":"540*304.gif","F+nXHM734QUm+ymw6IHvUg==":"tumblr_nlmanm99ai1qav3uso1-500.gif","Q46pnY/QQZPycU8fMzrULA==":"653-5.gif","5fLnT47snRUaUKYqjfRzXA==":"giphy.gif","Fmv9pzcIzbgzkzgaqymwOg==":"3dcityio-logo-white-1-178x162.png","M685RuVb/HThixtneI5Piw==":"face3.jpg","NPCTWpypqgDJtuIYouoC+A==":"face1.jpg","NABkP9i4t4mIGSpFn73WIA==":"background1.jpg","wtMHTTl7dGPg/yAYnv5I2g==":"giphy.gif","6YnAMIEzJwjDtSmNp0NCag==":"dr.gif","Q5iL16LYt1nDxkLC4deJNg==":"dr-500-min.gif","9Umto4qPXO2Zl36TFAf16Q==":"slam-zoomed.gif","Y/1QQudK6W4hs7Lrrxxl8w==":"slam.gif","acNraQhMST9Ewd/M0i0WQQ==":"nvidia-logo.png","6+P5+WA+Fsm+PF3tb3VdCg==":"nv.jpg","oaDSLb/xOU6/vviEZPPrcQ==":"nxp-logo.svg.png","gkTuVe8DwZy5HvHFumtQ8g==":"nxp.png","bV6AEf1D7AF12WvLMRpt9Q==":"nxp-1.png","scCPcQBXJ4AF3lY09ol7Ig==":"umbra-transparent-2000x654.png","BwKkVNrr6IyhhoQzeql84Q==":"umbra-transparent-1-2000x654.png","tmObqfEHs8d+ABNxdXOsDQ==":"umbra-transparent-2-2000x654.png","U17GQQxF6J7sh3b/QwAwGQ==":"connect-tech-logo.png","Lvn71Dl4KNNjjXi3UgVeJA==":"qualcomm-logo.png","pQAQcV6LKNcCVTCzwFA4uw==":"connect-tech-logo-white.png","nu43kUlXDVkr4yjQaO1Jww==":"connect-tech-logo-1.png","rGq474DKyMtpJhUWi1lLMQ==":"qualcomm-logo-1.png","oMjQPfHCYWzZ0cBJr3wYug==":"esri-logo-logotype.png","E+mG/WQN9mKjfoCgiP4kWw==":"esri-logo-logotype-copy.png","YDpdbs5aWfjaD7m+IfcQWw==":"esri-logo-logotype-white.png","1+vkam4YQ8IRIxyS4Rd2tA==":"esri-logo-logotype-white-1.png","uzVgbh4JghHs/u1IWpIsbA==":"newspons.jpg","Ab9IzBGlVjQC2jPBpCIbZQ==":"esri-logo-logotype-white-2.png","0JCtJk7nDVemUYqHMBg11g==":"aimldl-smartcity.jpg","bHsR17H1m4npz34XgM9WzA==":"8-cell-simple-1.gif","m+5oc0EWgAy7/Jd8/q9F+w==":"screen-shot-2018-07-25-at-11.24.47-am.png","gqdfGmwgwgmpa/MSRIY3zQ==":"aimldl-smartcity-1.jpg","1H1MLoZfgF0PPhLrEt/jMw==":"aimldl-smartcity-2.jpg","aRZWv0GppBGHHuvCWWuKCg==":"terrarium-2.gif","fmnv5Sf0gpgjTX0g/av/Ww==":"a.i.-in-the-cloud.gif","d8DGkMLFGjEeMo9CCohimw==":"ai-scheme-black-1.png","quMglcSHck5LXEdQJ7exFA==":"tca-scheme-black-1.png","Y4wlvdsCjqKgk1qUebCjPw==":"tca-scheme-black-2.png","AQ9wl0YYZdIL9KsU/NMOsQ==":"ai-scheme-black-2.png","/qkpd4UaXNf51K4RakWwaw==":"ai-scheme-black-3.png","E3CUdu4KMnwNUjmYMenBhA==":"ai-scheme-black-4.png","iJUW+EuQfhI7XYfQFbK5Tw==":"ai-scheme-black-5.png","J3JeBarMYj9VE+gh8FLGrg==":"ai-scheme-black-6.png","pF5MaM1YMMaragnojTZyjA==":"tca-scheme-black.png","LiUIORYxGXGMpCM1i0NnEA==":"06.jpg","ss0oYRgKTIR4EdPzwk9h7w==":"microtubule-transport.gif","lSmgbOxBzPhyP7cFz+9+1w==":"ai-scheme-black-7.png","0v90ZsqkLdflT6NlhuJsgg==":"ai-venn-3dcity.jpg","33rqwfmnbLfn5X8LdrRAtA==":"giphy-2.gif","pDgECbNuoXK5dB2pOsdmNQ==":"giphy-3.gif","D80vf2e2N/BIhP7ZSBIbaA==":"giphy-4.gif","AuHoNfyoD44NL/E4Lr5jJg==":"yflx.gif","RNuNEln7yA5n0Llu2bfktQ==":"4dmap.gif"}